LICENSE
MANIFEST.in
README.rst
setup.py
dj_sso_server.egg-info/PKG-INFO
dj_sso_server.egg-info/SOURCES.txt
dj_sso_server.egg-info/dependency_links.txt
dj_sso_server.egg-info/requires.txt
dj_sso_server.egg-info/top_level.txt
djssoserver/__init__.py
djssoserver/admin.py
djssoserver/apps.py
djssoserver/models.py
djssoserver/sso.py
djssoserver/tests.py
djssoserver/urls.py
djssoserver/utility.py
djssoserver/views.py
djssoserver/migrations/0001_initial.py
djssoserver/migrations/__init__.py
djssoserver/templates/djssoserver/ssologin.html
example/djssoserverapp/Procfile
example/djssoserverapp/db.sqlite3
example/djssoserverapp/initial_data.json
example/djssoserverapp/manage.py
example/djssoserverapp/requirements.txt
example/djssoserverapp/.idea/.name
example/djssoserverapp/.idea/djssoserverapp.iml
example/djssoserverapp/.idea/encodings.xml
example/djssoserverapp/.idea/misc.xml
example/djssoserverapp/.idea/modules.xml
example/djssoserverapp/.idea/vcs.xml
example/djssoserverapp/.idea/workspace.xml
example/djssoserverapp/.idea/inspectionProfiles/Project_Default.xml
example/djssoserverapp/.idea/inspectionProfiles/profiles_settings.xml
example/djssoserverapp/.idea/scopes/scope_settings.xml
example/djssoserverapp/djssoserverapp/__init__.py
example/djssoserverapp/djssoserverapp/__init__.pyc
example/djssoserverapp/djssoserverapp/settings.py
example/djssoserverapp/djssoserverapp/settings.pyc
example/djssoserverapp/djssoserverapp/urls.py
example/djssoserverapp/djssoserverapp/urls.pyc
example/djssoserverapp/djssoserverapp/views.py
example/djssoserverapp/djssoserverapp/views.pyc
example/djssoserverapp/djssoserverapp/wsgi.py
example/djssoserverapp/djssoserverapp/wsgi.pyc
example/djssoserverapp/templates/index.html
example/djssoserverapp/templates/registration/logged_out.html
example/djssoserverapp/templates/registration/login.html